{
  "_format": "ethers-rs-sol-cache-3",
  "paths": {
    "artifacts": "out",
    "build_infos": "out/build-info",
    "sources": "src",
    "tests": "test",
    "scripts": "script",
    "libraries": [
      "lib"
    ]
  },
  "files": {
    "lib/forge-std/lib/ds-test/src/test.sol": {
      "lastModificationDate": 1688710966224,
      "contentHash": "9febff9d09f18af5306669dc276c4c43",
      "sourceName": "lib/forge-std/lib/ds-test/src/test.sol",
      "solcConfig": {
        "settings": {
          "optimizer": {
            "enabled": true,
            "runs": 200
          },
          "metadata": {
            "bytecodeHash": "ipfs",
            "appendCBOR": true
          },
          "outputSelection": {
            "*": {
              "": [
                "ast"
              ],
              "*": [
                "abi",
                "evm.bytecode",
                "evm.deployedBytecode",
                "evm.methodIdentifiers",
                "metadata"
              ]
            }
          },
          "evmVersion": "paris",
          "libraries": {}
        }
      },
      "imports": [],
      "versionRequirement": ">=0.5.0",
      "artifacts": {
        "DSTest": {
          "0.8.19+commit.7dd6d404.Linux.gcc": "test.sol/DSTest.json"
        }
      }
    },
    "lib/forge-std/src/Base.sol": {
      "lastModificationDate": 1688710965164,
      "contentHash": "ee13c050b1914464f1d3f90cde90204b",
      "sourceName": "lib/forge-std/src/Base.sol",
      "solcConfig": {
        "settings": {
          "optimizer": {
            "enabled": true,
            "runs": 200
          },
          "metadata": {
            "bytecodeHash": "ipfs",
            "appendCBOR": true
          },
          "outputSelection": {
            "*": {
              "": [
                "ast"
              ],
              "*": [
                "abi",
                "evm.bytecode",
                "evm.deployedBytecode",
                "evm.methodIdentifiers",
                "metadata"
              ]
            }
          },
          "evmVersion": "paris",
          "libraries": {}
        }
      },
      "imports": [
        "lib/forge-std/src/StdStorage.sol",
        "lib/forge-std/src/Vm.sol"
      ],
      "versionRequirement": ">=0.6.2, <0.9.0",
      "artifacts": {
        "CommonBase": {
          "0.8.19+commit.7dd6d404.Linux.gcc": "Base.sol/CommonBase.json"
        },
        "ScriptBase": {
          "0.8.19+commit.7dd6d404.Linux.gcc": "Base.sol/ScriptBase.json"
        },
        "TestBase": {
          "0.8.19+commit.7dd6d404.Linux.gcc": "Base.sol/TestBase.json"
        }
      }
    },
    "lib/forge-std/src/Script.sol": {
      "lastModificationDate": 1688710966254,
      "contentHash": "83c39354c1e43190bce4dc43860dc786",
      "sourceName": "lib/forge-std/src/Script.sol",
      "solcConfig": {
        "settings": {
          "optimizer": {
            "enabled": true,
            "runs": 200
          },
          "metadata": {
            "bytecodeHash": "ipfs",
            "appendCBOR": true
          },
          "outputSelection": {
            "*": {
              "": [
                "ast"
              ],
              "*": [
                "abi",
                "evm.bytecode",
                "evm.deployedBytecode",
                "evm.methodIdentifiers",
                "metadata"
              ]
            }
          },
          "evmVersion": "paris",
          "libraries": {}
        }
      },
      "imports": [
        "lib/forge-std/src/Base.sol",
        "lib/forge-std/src/StdChains.sol",
        "lib/forge-std/src/StdCheats.sol",
        "lib/forge-std/src/StdJson.sol",
        "lib/forge-std/src/StdMath.sol",
        "lib/forge-std/src/StdStorage.sol",
        "lib/forge-std/src/StdUtils.sol",
        "lib/forge-std/src/Vm.sol",
        "lib/forge-std/src/console.sol",
        "lib/forge-std/src/console2.sol",
        "lib/forge-std/src/interfaces/IMulticall3.sol"
      ],
      "versionRequirement": ">=0.6.2, <0.9.0",
      "artifacts": {
        "Script": {
          "0.8.19+commit.7dd6d404.Linux.gcc": "Script.sol/Script.json"
        }
      }
    },
    "lib/forge-std/src/StdAssertions.sol": {
      "lastModificationDate": 1688710965164,
      "contentHash": "6cc2858240bcd443debbbf075490e325",
      "sourceName": "lib/forge-std/src/StdAssertions.sol",
      "solcConfig": {
        "settings": {
          "optimizer": {
            "enabled": true,
            "runs": 200
          },
          "metadata": {
            "bytecodeHash": "ipfs",
            "appendCBOR": true
          },
          "outputSelection": {
            "*": {
              "": [
                "ast"
              ],
              "*": [
                "abi",
                "evm.bytecode",
                "evm.deployedBytecode",
                "evm.methodIdentifiers",
                "metadata"
              ]
            }
          },
          "evmVersion": "paris",
          "libraries": {}
        }
      },
      "imports": [
        "lib/forge-std/lib/ds-test/src/test.sol",
        "lib/forge-std/src/StdMath.sol"
      ],
      "versionRequirement": ">=0.6.2, <0.9.0",
      "artifacts": {
        "StdAssertions": {
          "0.8.19+commit.7dd6d404.Linux.gcc": "StdAssertions.sol/StdAssertions.json"
        }
      }
    },
    "lib/forge-std/src/StdChains.sol": {
      "lastModificationDate": 1688710966254,
      "contentHash": "9c76820952c8f5e2fc02f872dc3afeb4",
      "sourceName": "lib/forge-std/src/StdChains.sol",
      "solcConfig": {
        "settings": {
          "optimizer": {
            "enabled": true,
            "runs": 200
          },
          "metadata": {
            "bytecodeHash": "ipfs",
            "appendCBOR": true
          },
          "outputSelection": {
            "*": {
              "": [
                "ast"
              ],
              "*": [
                "abi",
                "evm.bytecode",
                "evm.deployedBytecode",
                "evm.methodIdentifiers",
                "metadata"
              ]
            }
          },
          "evmVersion": "paris",
          "libraries": {}
        }
      },
      "imports": [
        "lib/forge-std/src/Vm.sol"
      ],
      "versionRequirement": ">=0.6.2, <0.9.0",
      "artifacts": {
        "StdChains": {
          "0.8.19+commit.7dd6d404.Linux.gcc": "StdChains.sol/StdChains.json"
        }
      }
    },
    "lib/forge-std/src/StdCheats.sol": {
      "lastModificationDate": 1688710966254,
      "contentHash": "24785368b480beef5cd536afd144d5cb",
      "sourceName": "lib/forge-std/src/StdCheats.sol",
      "solcConfig": {
        "settings": {
          "optimizer": {
            "enabled": true,
            "runs": 200
          },
          "metadata": {
            "bytecodeHash": "ipfs",
            "appendCBOR": true
          },
          "outputSelection": {
            "*": {
              "": [
                "ast"
              ],
              "*": [
                "abi",
                "evm.bytecode",
                "evm.deployedBytecode",
                "evm.methodIdentifiers",
                "metadata"
              ]
            }
          },
          "evmVersion": "paris",
          "libraries": {}
        }
      },
      "imports": [
        "lib/forge-std/src/StdStorage.sol",
        "lib/forge-std/src/Vm.sol",
        "lib/forge-std/src/console2.sol"
      ],
      "versionRequirement": ">=0.6.2, <0.9.0",
      "artifacts": {
        "StdCheats": {
          "0.8.19+commit.7dd6d404.Linux.gcc": "StdCheats.sol/StdCheats.json"
        },
        "StdCheatsSafe": {
          "0.8.19+commit.7dd6d404.Linux.gcc": "StdCheats.sol/StdCheatsSafe.json"
        }
      }
    },
    "lib/forge-std/src/StdError.sol": {
      "lastModificationDate": 1688710965164,
      "contentHash": "64c896e1276a291776e5ea5aecb3870a",
      "sourceName": "lib/forge-std/src/StdError.sol",
      "solcConfig": {
        "settings": {
          "optimizer": {
            "enabled": true,
            "runs": 200
          },
          "metadata": {
            "bytecodeHash": "ipfs",
            "appendCBOR": true
          },
          "outputSelection": {
            "*": {
              "": [
                "ast"
              ],
              "*": [
                "abi",
                "evm.bytecode",
                "evm.deployedBytecode",
                "evm.methodIdentifiers",
                "metadata"
              ]
            }
          },
          "evmVersion": "paris",
          "libraries": {}
        }
      },
      "imports": [],
      "versionRequirement": ">=0.6.2, <0.9.0",
      "artifacts": {
        "stdError": {
          "0.8.19+commit.7dd6d404.Linux.gcc": "StdError.sol/stdError.json"
        }
      }
    },
    "lib/forge-std/src/StdInvariant.sol": {
      "lastModificationDate": 1688710966254,
      "contentHash": "12c06010ec43ce935ed209d5aca30828",
      "sourceName": "lib/forge-std/src/StdInvariant.sol",
      "solcConfig": {
        "settings": {
          "optimizer": {
            "enabled": true,
            "runs": 200
          },
          "metadata": {
            "bytecodeHash": "ipfs",
            "appendCBOR": true
          },
          "outputSelection": {
            "*": {
              "": [
                "ast"
              ],
              "*": [
                "abi",
                "evm.bytecode",
                "evm.deployedBytecode",
                "evm.methodIdentifiers",
                "metadata"
              ]
            }
          },
          "evmVersion": "paris",
          "libraries": {}
        }
      },
      "imports": [],
      "versionRequirement": ">=0.6.2, <0.9.0",
      "artifacts": {
        "StdInvariant": {
          "0.8.19+commit.7dd6d404.Linux.gcc": "StdInvariant.sol/StdInvariant.json"
        }
      }
    },
    "lib/forge-std/src/StdJson.sol": {
      "lastModificationDate": 1688710965164,
      "contentHash": "2e1d13674e152408867795362d833c24",
      "sourceName": "lib/forge-std/src/StdJson.sol",
      "solcConfig": {
        "settings": {
          "optimizer": {
            "enabled": true,
            "runs": 200
          },
          "metadata": {
            "bytecodeHash": "ipfs",
            "appendCBOR": true
          },
          "outputSelection": {
            "*": {
              "": [
                "ast"
              ],
              "*": [
                "abi",
                "evm.bytecode",
                "evm.deployedBytecode",
                "evm.methodIdentifiers",
                "metadata"
              ]
            }
          },
          "evmVersion": "paris",
          "libraries": {}
        }
      },
      "imports": [
        "lib/forge-std/src/Vm.sol"
      ],
      "versionRequirement": ">=0.6.0, <0.9.0",
      "artifacts": {
        "stdJson": {
          "0.8.19+commit.7dd6d404.Linux.gcc": "StdJson.sol/stdJson.json"
        }
      }
    },
    "lib/forge-std/src/StdMath.sol": {
      "lastModificationDate": 1688710965164,
      "contentHash": "9da8f453eba6bb98f3d75bc6822bfb29",
      "sourceName": "lib/forge-std/src/StdMath.sol",
      "solcConfig": {
        "settings": {
          "optimizer": {
            "enabled": true,
            "runs": 200
          },
          "metadata": {
            "bytecodeHash": "ipfs",
            "appendCBOR": true
          },
          "outputSelection": {
            "*": {
              "": [
                "ast"
              ],
              "*": [
                "abi",
                "evm.bytecode",
                "evm.deployedBytecode",
                "evm.methodIdentifiers",
                "metadata"
              ]
            }
          },
          "evmVersion": "paris",
          "libraries": {}
        }
      },
      "imports": [],
      "versionRequirement": ">=0.6.2, <0.9.0",
      "artifacts": {
        "stdMath": {
          "0.8.19+commit.7dd6d404.Linux.gcc": "StdMath.sol/stdMath.json"
        }
      }
    },
    "lib/forge-std/src/StdStorage.sol": {
      "lastModificationDate": 1688710965164,
      "contentHash": "3cb9868082df39a53927db09dbc21f23",
      "sourceName": "lib/forge-std/src/StdStorage.sol",
      "solcConfig": {
        "settings": {
          "optimizer": {
            "enabled": true,
            "runs": 200
          },
          "metadata": {
            "bytecodeHash": "ipfs",
            "appendCBOR": true
          },
          "outputSelection": {
            "*": {
              "": [
                "ast"
              ],
              "*": [
                "abi",
                "evm.bytecode",
                "evm.deployedBytecode",
                "evm.methodIdentifiers",
                "metadata"
              ]
            }
          },
          "evmVersion": "paris",
          "libraries": {}
        }
      },
      "imports": [
        "lib/forge-std/src/Vm.sol"
      ],
      "versionRequirement": ">=0.6.2, <0.9.0",
      "artifacts": {
        "stdStorage": {
          "0.8.19+commit.7dd6d404.Linux.gcc": "StdStorage.sol/stdStorage.json"
        },
        "stdStorageSafe": {
          "0.8.19+commit.7dd6d404.Linux.gcc": "StdStorage.sol/stdStorageSafe.json"
        }
      }
    },
    "lib/forge-std/src/StdStyle.sol": {
      "lastModificationDate": 1688710966254,
      "contentHash": "820e6f6b7704f0c980fae604b1e34b18",
      "sourceName": "lib/forge-std/src/StdStyle.sol",
      "solcConfig": {
        "settings": {
          "optimizer": {
            "enabled": true,
            "runs": 200
          },
          "metadata": {
            "bytecodeHash": "ipfs",
            "appendCBOR": true
          },
          "outputSelection": {
            "*": {
              "": [
                "ast"
              ],
              "*": [
                "abi",
                "evm.bytecode",
                "evm.deployedBytecode",
                "evm.methodIdentifiers",
                "metadata"
              ]
            }
          },
          "evmVersion": "paris",
          "libraries": {}
        }
      },
      "imports": [
        "lib/forge-std/src/Vm.sol"
      ],
      "versionRequirement": ">=0.4.22, <0.9.0",
      "artifacts": {
        "StdStyle": {
          "0.8.19+commit.7dd6d404.Linux.gcc": "StdStyle.sol/StdStyle.json"
        }
      }
    },
    "lib/forge-std/src/StdUtils.sol": {
      "lastModificationDate": 1688710966254,
      "contentHash": "dd923493ddd9f98777687205cfe9d646",
      "sourceName": "lib/forge-std/src/StdUtils.sol",
      "solcConfig": {
        "settings": {
          "optimizer": {
            "enabled": true,
            "runs": 200
          },
          "metadata": {
            "bytecodeHash": "ipfs",
            "appendCBOR": true
          },
          "outputSelection": {
            "*": {
              "": [
                "ast"
              ],
              "*": [
                "abi",
                "evm.bytecode",
                "evm.deployedBytecode",
                "evm.methodIdentifiers",
                "metadata"
              ]
            }
          },
          "evmVersion": "paris",
          "libraries": {}
        }
      },
      "imports": [
        "lib/forge-std/src/Vm.sol",
        "lib/forge-std/src/interfaces/IMulticall3.sol"
      ],
      "versionRequirement": ">=0.6.2, <0.9.0",
      "artifacts": {
        "StdUtils": {
          "0.8.19+commit.7dd6d404.Linux.gcc": "StdUtils.sol/StdUtils.json"
        }
      }
    },
    "lib/forge-std/src/Test.sol": {
      "lastModificationDate": 1688710966254,
      "contentHash": "bc9d74a0c612e1c2b66cca2973bcc803",
      "sourceName": "lib/forge-std/src/Test.sol",
      "solcConfig": {
        "settings": {
          "optimizer": {
            "enabled": true,
            "runs": 200
          },
          "metadata": {
            "bytecodeHash": "ipfs",
            "appendCBOR": true
          },
          "outputSelection": {
            "*": {
              "": [
                "ast"
              ],
              "*": [
                "abi",
                "evm.bytecode",
                "evm.deployedBytecode",
                "evm.methodIdentifiers",
                "metadata"
              ]
            }
          },
          "evmVersion": "paris",
          "libraries": {}
        }
      },
      "imports": [
        "lib/forge-std/lib/ds-test/src/test.sol",
        "lib/forge-std/src/Base.sol",
        "lib/forge-std/src/StdAssertions.sol",
        "lib/forge-std/src/StdChains.sol",
        "lib/forge-std/src/StdCheats.sol",
        "lib/forge-std/src/StdError.sol",
        "lib/forge-std/src/StdInvariant.sol",
        "lib/forge-std/src/StdJson.sol",
        "lib/forge-std/src/StdMath.sol",
        "lib/forge-std/src/StdStorage.sol",
        "lib/forge-std/src/StdStyle.sol",
        "lib/forge-std/src/StdUtils.sol",
        "lib/forge-std/src/Vm.sol",
        "lib/forge-std/src/console.sol",
        "lib/forge-std/src/console2.sol",
        "lib/forge-std/src/interfaces/IMulticall3.sol"
      ],
      "versionRequirement": ">=0.6.2, <0.9.0",
      "artifacts": {
        "Test": {
          "0.8.19+commit.7dd6d404.Linux.gcc": "Test.sol/Test.json"
        }
      }
    },
    "lib/forge-std/src/Vm.sol": {
      "lastModificationDate": 1688710966254,
      "contentHash": "93cbedbadc52c20145ebbfa27ce148c4",
      "sourceName": "lib/forge-std/src/Vm.sol",
      "solcConfig": {
        "settings": {
          "optimizer": {
            "enabled": true,
            "runs": 200
          },
          "metadata": {
            "bytecodeHash": "ipfs",
            "appendCBOR": true
          },
          "outputSelection": {
            "*": {
              "": [
                "ast"
              ],
              "*": [
                "abi",
                "evm.bytecode",
                "evm.deployedBytecode",
                "evm.methodIdentifiers",
                "metadata"
              ]
            }
          },
          "evmVersion": "paris",
          "libraries": {}
        }
      },
      "imports": [],
      "versionRequirement": ">=0.6.2, <0.9.0",
      "artifacts": {
        "Vm": {
          "0.8.19+commit.7dd6d404.Linux.gcc": "Vm.sol/Vm.json"
        },
        "VmSafe": {
          "0.8.19+commit.7dd6d404.Linux.gcc": "Vm.sol/VmSafe.json"
        }
      }
    },
    "lib/forge-std/src/console.sol": {
      "lastModificationDate": 1688710965164,
      "contentHash": "100b8a33b917da1147740d7ab8b0ded3",
      "sourceName": "lib/forge-std/src/console.sol",
      "solcConfig": {
        "settings": {
          "optimizer": {
            "enabled": true,
            "runs": 200
          },
          "metadata": {
            "bytecodeHash": "ipfs",
            "appendCBOR": true
          },
          "outputSelection": {
            "*": {
              "": [
                "ast"
              ],
              "*": [
                "abi",
                "evm.bytecode",
                "evm.deployedBytecode",
                "evm.methodIdentifiers",
                "metadata"
              ]
            }
          },
          "evmVersion": "paris",
          "libraries": {}
        }
      },
      "imports": [],
      "versionRequirement": ">=0.4.22, <0.9.0",
      "artifacts": {
        "console": {
          "0.8.19+commit.7dd6d404.Linux.gcc": "console.sol/console.json"
        }
      }
    },
    "lib/forge-std/src/console2.sol": {
      "lastModificationDate": 1688710965164,
      "contentHash": "491ca717c1915995e78cc361485a3067",
      "sourceName": "lib/forge-std/src/console2.sol",
      "solcConfig": {
        "settings": {
          "optimizer": {
            "enabled": true,
            "runs": 200
          },
          "metadata": {
            "bytecodeHash": "ipfs",
            "appendCBOR": true
          },
          "outputSelection": {
            "*": {
              "": [
                "ast"
              ],
              "*": [
                "abi",
                "evm.bytecode",
                "evm.deployedBytecode",
                "evm.methodIdentifiers",
                "metadata"
              ]
            }
          },
          "evmVersion": "paris",
          "libraries": {}
        }
      },
      "imports": [],
      "versionRequirement": ">=0.4.22, <0.9.0",
      "artifacts": {
        "console2": {
          "0.8.19+commit.7dd6d404.Linux.gcc": "console2.sol/console2.json"
        }
      }
    },
    "lib/forge-std/src/interfaces/IMulticall3.sol": {
      "lastModificationDate": 1688710965164,
      "contentHash": "7b131ca1ca32ef6378b7b9ad5488b901",
      "sourceName": "lib/forge-std/src/interfaces/IMulticall3.sol",
      "solcConfig": {
        "settings": {
          "optimizer": {
            "enabled": true,
            "runs": 200
          },
          "metadata": {
            "bytecodeHash": "ipfs",
            "appendCBOR": true
          },
          "outputSelection": {
            "*": {
              "": [
                "ast"
              ],
              "*": [
                "abi",
                "evm.bytecode",
                "evm.deployedBytecode",
                "evm.methodIdentifiers",
                "metadata"
              ]
            }
          },
          "evmVersion": "paris",
          "libraries": {}
        }
      },
      "imports": [],
      "versionRequirement": ">=0.6.2, <0.9.0",
      "artifacts": {
        "IMulticall3": {
          "0.8.19+commit.7dd6d404.Linux.gcc": "IMulticall3.sol/IMulticall3.json"
        }
      }
    },
    "lib/openzeppelin-contracts/contracts/token/ERC20/ERC20.sol": {
      "lastModificationDate": 1688711625004,
      "contentHash": "3ae5166c6827a9cf1a7a462d1632b464",
      "sourceName": "lib/openzeppelin-contracts/contracts/token/ERC20/ERC20.sol",
      "solcConfig": {
        "settings": {
          "optimizer": {
            "enabled": true,
            "runs": 200
          },
          "metadata": {
            "bytecodeHash": "ipfs",
            "appendCBOR": true
          },
          "outputSelection": {
            "*": {
              "": [
                "ast"
              ],
              "*": [
                "abi",
                "evm.bytecode",
                "evm.deployedBytecode",
                "evm.methodIdentifiers",
                "metadata"
              ]
            }
          },
          "evmVersion": "paris",
          "libraries": {}
        }
      },
      "imports": [
        "lib/openzeppelin-contracts/contracts/token/ERC20/IERC20.sol",
        "lib/openzeppelin-contracts/contracts/token/ERC20/extensions/IERC20Metadata.sol",
        "lib/openzeppelin-contracts/contracts/utils/Context.sol"
      ],
      "versionRequirement": "^0.8.0",
      "artifacts": {
        "ERC20": {
          "0.8.19+commit.7dd6d404.Linux.gcc": "ERC20.sol/ERC20.json"
        }
      }
    },
    "lib/openzeppelin-contracts/contracts/token/ERC20/IERC20.sol": {
      "lastModificationDate": 1688711625004,
      "contentHash": "df36f7051335cd1e748b1b6463b7fdd3",
      "sourceName": "lib/openzeppelin-contracts/contracts/token/ERC20/IERC20.sol",
      "solcConfig": {
        "settings": {
          "optimizer": {
            "enabled": true,
            "runs": 200
          },
          "metadata": {
            "bytecodeHash": "ipfs",
            "appendCBOR": true
          },
          "outputSelection": {
            "*": {
              "": [
                "ast"
              ],
              "*": [
                "abi",
                "evm.bytecode",
                "evm.deployedBytecode",
                "evm.methodIdentifiers",
                "metadata"
              ]
            }
          },
          "evmVersion": "paris",
          "libraries": {}
        }
      },
      "imports": [],
      "versionRequirement": "^0.8.0",
      "artifacts": {
        "IERC20": {
          "0.8.19+commit.7dd6d404.Linux.gcc": "IERC20.sol/IERC20.json"
        }
      }
    },
    "lib/openzeppelin-contracts/contracts/token/ERC20/extensions/IERC20Metadata.sol": {
      "lastModificationDate": 1688711625004,
      "contentHash": "909ab67fc5c25033fe6cd364f8c056f9",
      "sourceName": "lib/openzeppelin-contracts/contracts/token/ERC20/extensions/IERC20Metadata.sol",
      "solcConfig": {
        "settings": {
          "optimizer": {
            "enabled": true,
            "runs": 200
          },
          "metadata": {
            "bytecodeHash": "ipfs",
            "appendCBOR": true
          },
          "outputSelection": {
            "*": {
              "": [
                "ast"
              ],
              "*": [
                "abi",
                "evm.bytecode",
                "evm.deployedBytecode",
                "evm.methodIdentifiers",
                "metadata"
              ]
            }
          },
          "evmVersion": "paris",
          "libraries": {}
        }
      },
      "imports": [
        "lib/openzeppelin-contracts/contracts/token/ERC20/IERC20.sol"
      ],
      "versionRequirement": "^0.8.0",
      "artifacts": {
        "IERC20Metadata": {
          "0.8.19+commit.7dd6d404.Linux.gcc": "IERC20Metadata.sol/IERC20Metadata.json"
        }
      }
    },
    "lib/openzeppelin-contracts/contracts/utils/Context.sol": {
      "lastModificationDate": 1688711625004,
      "contentHash": "5f2c5c4b6af2dd4551027144797bc8be",
      "sourceName": "lib/openzeppelin-contracts/contracts/utils/Context.sol",
      "solcConfig": {
        "settings": {
          "optimizer": {
            "enabled": true,
            "runs": 200
          },
          "metadata": {
            "bytecodeHash": "ipfs",
            "appendCBOR": true
          },
          "outputSelection": {
            "*": {
              "": [
                "ast"
              ],
              "*": [
                "abi",
                "evm.bytecode",
                "evm.deployedBytecode",
                "evm.methodIdentifiers",
                "metadata"
              ]
            }
          },
          "evmVersion": "paris",
          "libraries": {}
        }
      },
      "imports": [],
      "versionRequirement": "^0.8.0",
      "artifacts": {
        "Context": {
          "0.8.19+commit.7dd6d404.Linux.gcc": "Context.sol/Context.json"
        }
      }
    },
    "script/DeployOutToken.s.sol": {
      "lastModificationDate": 1688712709834,
      "contentHash": "b667a030479860ab95c499e034bed9a4",
      "sourceName": "script/DeployOutToken.s.sol",
      "solcConfig": {
        "settings": {
          "optimizer": {
            "enabled": true,
            "runs": 200
          },
          "metadata": {
            "bytecodeHash": "ipfs",
            "appendCBOR": true
          },
          "outputSelection": {
            "*": {
              "": [
                "ast"
              ],
              "*": [
                "abi",
                "evm.bytecode",
                "evm.deployedBytecode",
                "evm.methodIdentifiers",
                "metadata"
              ]
            }
          },
          "evmVersion": "paris",
          "libraries": {}
        }
      },
      "imports": [
        "lib/forge-std/src/Base.sol",
        "lib/forge-std/src/Script.sol",
        "lib/forge-std/src/StdChains.sol",
        "lib/forge-std/src/StdCheats.sol",
        "lib/forge-std/src/StdJson.sol",
        "lib/forge-std/src/StdMath.sol",
        "lib/forge-std/src/StdStorage.sol",
        "lib/forge-std/src/StdUtils.sol",
        "lib/forge-std/src/Vm.sol",
        "lib/forge-std/src/console.sol",
        "lib/forge-std/src/console2.sol",
        "lib/forge-std/src/interfaces/IMulticall3.sol",
        "lib/openzeppelin-contracts/contracts/token/ERC20/ERC20.sol",
        "lib/openzeppelin-contracts/contracts/token/ERC20/IERC20.sol",
        "lib/openzeppelin-contracts/contracts/token/ERC20/extensions/IERC20Metadata.sol",
        "lib/openzeppelin-contracts/contracts/utils/Context.sol",
        "src/OurToken.sol"
      ],
      "versionRequirement": "^0.8.18",
      "artifacts": {
        "DeployOurToken": {
          "0.8.19+commit.7dd6d404.Linux.gcc": "DeployOutToken.s.sol/DeployOurToken.json"
        }
      }
    },
    "src/ManualToken.sol": {
      "lastModificationDate": 1688711483944,
      "contentHash": "a4dcb6096679fad6ad3dfb56c49342a6",
      "sourceName": "src/ManualToken.sol",
      "solcConfig": {
        "settings": {
          "optimizer": {
            "enabled": true,
            "runs": 200
          },
          "metadata": {
            "bytecodeHash": "ipfs",
            "appendCBOR": true
          },
          "outputSelection": {
            "*": {
              "": [
                "ast"
              ],
              "*": [
                "abi",
                "evm.bytecode",
                "evm.deployedBytecode",
                "evm.methodIdentifiers",
                "metadata"
              ]
            }
          },
          "evmVersion": "paris",
          "libraries": {}
        }
      },
      "imports": [],
      "versionRequirement": "^0.8.18",
      "artifacts": {
        "ManualToken": {
          "0.8.19+commit.7dd6d404.Linux.gcc": "ManualToken.sol/ManualToken.json"
        }
      }
    },
    "src/OurToken.sol": {
      "lastModificationDate": 1688712308794,
      "contentHash": "a535b359910b54dc05b12b2a0d1a7d72",
      "sourceName": "src/OurToken.sol",
      "solcConfig": {
        "settings": {
          "optimizer": {
            "enabled": true,
            "runs": 200
          },
          "metadata": {
            "bytecodeHash": "ipfs",
            "appendCBOR": true
          },
          "outputSelection": {
            "*": {
              "": [
                "ast"
              ],
              "*": [
                "abi",
                "evm.bytecode",
                "evm.deployedBytecode",
                "evm.methodIdentifiers",
                "metadata"
              ]
            }
          },
          "evmVersion": "paris",
          "libraries": {}
        }
      },
      "imports": [
        "lib/openzeppelin-contracts/contracts/token/ERC20/ERC20.sol",
        "lib/openzeppelin-contracts/contracts/token/ERC20/IERC20.sol",
        "lib/openzeppelin-contracts/contracts/token/ERC20/extensions/IERC20Metadata.sol",
        "lib/openzeppelin-contracts/contracts/utils/Context.sol"
      ],
      "versionRequirement": "^0.8.18",
      "artifacts": {
        "OurToken": {
          "0.8.19+commit.7dd6d404.Linux.gcc": "OurToken.sol/OurToken.json"
        }
      }
    },
    "test/OurTokenTest.t.sol": {
      "lastModificationDate": 1688714301105,
      "contentHash": "14b44bff39e92f30000026b6dac50011",
      "sourceName": "test/OurTokenTest.t.sol",
      "solcConfig": {
        "settings": {
          "optimizer": {
            "enabled": true,
            "runs": 200
          },
          "metadata": {
            "bytecodeHash": "ipfs",
            "appendCBOR": true
          },
          "outputSelection": {
            "*": {
              "": [
                "ast"
              ],
              "*": [
                "abi",
                "evm.bytecode",
                "evm.deployedBytecode",
                "evm.methodIdentifiers",
                "metadata"
              ]
            }
          },
          "evmVersion": "paris",
          "libraries": {}
        }
      },
      "imports": [
        "lib/forge-std/lib/ds-test/src/test.sol",
        "lib/forge-std/src/Base.sol",
        "lib/forge-std/src/Script.sol",
        "lib/forge-std/src/StdAssertions.sol",
        "lib/forge-std/src/StdChains.sol",
        "lib/forge-std/src/StdCheats.sol",
        "lib/forge-std/src/StdError.sol",
        "lib/forge-std/src/StdInvariant.sol",
        "lib/forge-std/src/StdJson.sol",
        "lib/forge-std/src/StdMath.sol",
        "lib/forge-std/src/StdStorage.sol",
        "lib/forge-std/src/StdStyle.sol",
        "lib/forge-std/src/StdUtils.sol",
        "lib/forge-std/src/Test.sol",
        "lib/forge-std/src/Vm.sol",
        "lib/forge-std/src/console.sol",
        "lib/forge-std/src/console2.sol",
        "lib/forge-std/src/interfaces/IMulticall3.sol",
        "lib/openzeppelin-contracts/contracts/token/ERC20/ERC20.sol",
        "lib/openzeppelin-contracts/contracts/token/ERC20/IERC20.sol",
        "lib/openzeppelin-contracts/contracts/token/ERC20/extensions/IERC20Metadata.sol",
        "lib/openzeppelin-contracts/contracts/utils/Context.sol",
        "script/DeployOutToken.s.sol",
        "src/OurToken.sol"
      ],
      "versionRequirement": "^0.8.18",
      "artifacts": {
        "OurTokenTest": {
          "0.8.19+commit.7dd6d404.Linux.gcc": "OurTokenTest.t.sol/OurTokenTest.json"
        }
      }
    }
  }
}