{
  "_format": "ethers-rs-sol-cache-3",
  "paths": {
    "artifacts": "out",
    "build_infos": "out/build-info",
    "sources": "src",
    "tests": "test",
    "scripts": "script",
    "libraries": [
      "lib"
    ]
  },
  "files": {
    "lib/chainlink-brownie-contracts/contracts/src/v0.8/VRFConsumerBaseV2.sol": {
      "lastModificationDate": 1688576278410,
      "contentHash": "eb9cc526ef59dfc4d644f56ddca0633a",
      "sourceName": "lib/chainlink-brownie-contracts/contracts/src/v0.8/VRFConsumerBaseV2.sol",
      "solcConfig": {
        "settings": {
          "optimizer": {
            "enabled": true,
            "runs": 200
          },
          "metadata": {
            "bytecodeHash": "ipfs",
            "appendCBOR": true
          },
          "outputSelection": {
            "*": {
              "": [
                "ast"
              ],
              "*": [
                "abi",
                "evm.bytecode",
                "evm.deployedBytecode",
                "evm.methodIdentifiers",
                "metadata"
              ]
            }
          },
          "evmVersion": "paris",
          "libraries": {}
        }
      },
      "imports": [],
      "versionRequirement": "^0.8.4",
      "artifacts": {
        "VRFConsumerBaseV2": {
          "0.8.19+commit.7dd6d404.Linux.gcc": "VRFConsumerBaseV2.sol/VRFConsumerBaseV2.json"
        }
      }
    },
    "lib/chainlink-brownie-contracts/contracts/src/v0.8/interfaces/LinkTokenInterface.sol": {
      "lastModificationDate": 1688576278440,
      "contentHash": "da5a0c3bd86c896f6a407f909c57edf3",
      "sourceName": "lib/chainlink-brownie-contracts/contracts/src/v0.8/interfaces/LinkTokenInterface.sol",
      "solcConfig": {
        "settings": {
          "optimizer": {
            "enabled": true,
            "runs": 200
          },
          "metadata": {
            "bytecodeHash": "ipfs",
            "appendCBOR": true
          },
          "outputSelection": {
            "*": {
              "": [
                "ast"
              ],
              "*": [
                "abi",
                "evm.bytecode",
                "evm.deployedBytecode",
                "evm.methodIdentifiers",
                "metadata"
              ]
            }
          },
          "evmVersion": "paris",
          "libraries": {}
        }
      },
      "imports": [],
      "versionRequirement": "^0.8.0",
      "artifacts": {
        "LinkTokenInterface": {
          "0.8.19+commit.7dd6d404.Linux.gcc": "LinkTokenInterface.sol/LinkTokenInterface.json"
        }
      }
    },
    "lib/chainlink-brownie-contracts/contracts/src/v0.8/interfaces/VRFCoordinatorV2Interface.sol": {
      "lastModificationDate": 1688576278440,
      "contentHash": "8c9ed3426b676f67ee200a2bec96e224",
      "sourceName": "lib/chainlink-brownie-contracts/contracts/src/v0.8/interfaces/VRFCoordinatorV2Interface.sol",
      "solcConfig": {
        "settings": {
          "optimizer": {
            "enabled": true,
            "runs": 200
          },
          "metadata": {
            "bytecodeHash": "ipfs",
            "appendCBOR": true
          },
          "outputSelection": {
            "*": {
              "": [
                "ast"
              ],
              "*": [
                "abi",
                "evm.bytecode",
                "evm.deployedBytecode",
                "evm.methodIdentifiers",
                "metadata"
              ]
            }
          },
          "evmVersion": "paris",
          "libraries": {}
        }
      },
      "imports": [],
      "versionRequirement": "^0.8.0",
      "artifacts": {
        "VRFCoordinatorV2Interface": {
          "0.8.19+commit.7dd6d404.Linux.gcc": "VRFCoordinatorV2Interface.sol/VRFCoordinatorV2Interface.json"
        }
      }
    },
    "lib/chainlink-brownie-contracts/contracts/src/v0.8/mocks/VRFCoordinatorV2Mock.sol": {
      "lastModificationDate": 1688576278440,
      "contentHash": "a78f72f6c18077e727bc06d7f96b2031",
      "sourceName": "lib/chainlink-brownie-contracts/contracts/src/v0.8/mocks/VRFCoordinatorV2Mock.sol",
      "solcConfig": {
        "settings": {
          "optimizer": {
            "enabled": true,
            "runs": 200
          },
          "metadata": {
            "bytecodeHash": "ipfs",
            "appendCBOR": true
          },
          "outputSelection": {
            "*": {
              "": [
                "ast"
              ],
              "*": [
                "abi",
                "evm.bytecode",
                "evm.deployedBytecode",
                "evm.methodIdentifiers",
                "metadata"
              ]
            }
          },
          "evmVersion": "paris",
          "libraries": {}
        }
      },
      "imports": [
        "lib/chainlink-brownie-contracts/contracts/src/v0.8/VRFConsumerBaseV2.sol",
        "lib/chainlink-brownie-contracts/contracts/src/v0.8/interfaces/LinkTokenInterface.sol",
        "lib/chainlink-brownie-contracts/contracts/src/v0.8/interfaces/VRFCoordinatorV2Interface.sol"
      ],
      "versionRequirement": "^0.8.4",
      "artifacts": {
        "VRFCoordinatorV2Mock": {
          "0.8.19+commit.7dd6d404.Linux.gcc": "VRFCoordinatorV2Mock.sol/VRFCoordinatorV2Mock.json"
        }
      }
    },
    "lib/forge-std/src/Base.sol": {
      "lastModificationDate": 1688573037001,
      "contentHash": "ee13c050b1914464f1d3f90cde90204b",
      "sourceName": "lib/forge-std/src/Base.sol",
      "solcConfig": {
        "settings": {
          "optimizer": {
            "enabled": true,
            "runs": 200
          },
          "metadata": {
            "bytecodeHash": "ipfs",
            "appendCBOR": true
          },
          "outputSelection": {
            "*": {
              "": [
                "ast"
              ],
              "*": [
                "abi",
                "evm.bytecode",
                "evm.deployedBytecode",
                "evm.methodIdentifiers",
                "metadata"
              ]
            }
          },
          "evmVersion": "paris",
          "libraries": {}
        }
      },
      "imports": [
        "lib/forge-std/src/StdStorage.sol",
        "lib/forge-std/src/Vm.sol"
      ],
      "versionRequirement": ">=0.6.2, <0.9.0",
      "artifacts": {
        "CommonBase": {
          "0.8.19+commit.7dd6d404.Linux.gcc": "Base.sol/CommonBase.json"
        },
        "ScriptBase": {
          "0.8.19+commit.7dd6d404.Linux.gcc": "Base.sol/ScriptBase.json"
        },
        "TestBase": {
          "0.8.19+commit.7dd6d404.Linux.gcc": "Base.sol/TestBase.json"
        }
      }
    },
    "lib/forge-std/src/Script.sol": {
      "lastModificationDate": 1688573043851,
      "contentHash": "83c39354c1e43190bce4dc43860dc786",
      "sourceName": "lib/forge-std/src/Script.sol",
      "solcConfig": {
        "settings": {
          "optimizer": {
            "enabled": true,
            "runs": 200
          },
          "metadata": {
            "bytecodeHash": "ipfs",
            "appendCBOR": true
          },
          "outputSelection": {
            "*": {
              "": [
                "ast"
              ],
              "*": [
                "abi",
                "evm.bytecode",
                "evm.deployedBytecode",
                "evm.methodIdentifiers",
                "metadata"
              ]
            }
          },
          "evmVersion": "paris",
          "libraries": {}
        }
      },
      "imports": [
        "lib/forge-std/src/Base.sol",
        "lib/forge-std/src/StdChains.sol",
        "lib/forge-std/src/StdCheats.sol",
        "lib/forge-std/src/StdJson.sol",
        "lib/forge-std/src/StdMath.sol",
        "lib/forge-std/src/StdStorage.sol",
        "lib/forge-std/src/StdUtils.sol",
        "lib/forge-std/src/Vm.sol",
        "lib/forge-std/src/console.sol",
        "lib/forge-std/src/console2.sol",
        "lib/forge-std/src/interfaces/IMulticall3.sol"
      ],
      "versionRequirement": ">=0.6.2, <0.9.0",
      "artifacts": {
        "Script": {
          "0.8.19+commit.7dd6d404.Linux.gcc": "Script.sol/Script.json"
        }
      }
    },
    "lib/forge-std/src/StdAssertions.sol": {
      "lastModificationDate": 1688573037001,
      "contentHash": "6cc2858240bcd443debbbf075490e325",
      "sourceName": "lib/forge-std/src/StdAssertions.sol",
      "solcConfig": {
        "settings": {
          "optimizer": {
            "enabled": true,
            "runs": 200
          },
          "metadata": {
            "bytecodeHash": "ipfs",
            "appendCBOR": true
          },
          "outputSelection": {
            "*": {
              "": [
                "ast"
              ],
              "*": [
                "abi",
                "evm.bytecode",
                "evm.deployedBytecode",
                "evm.methodIdentifiers",
                "metadata"
              ]
            }
          },
          "evmVersion": "paris",
          "libraries": {}
        }
      },
      "imports": [
        "lib/forge-std/src/StdMath.sol",
        "lib/solmate/lib/ds-test/src/test.sol"
      ],
      "versionRequirement": ">=0.6.2, <0.9.0",
      "artifacts": {
        "StdAssertions": {
          "0.8.19+commit.7dd6d404.Linux.gcc": "StdAssertions.sol/StdAssertions.json"
        }
      }
    },
    "lib/forge-std/src/StdChains.sol": {
      "lastModificationDate": 1688573043851,
      "contentHash": "9c76820952c8f5e2fc02f872dc3afeb4",
      "sourceName": "lib/forge-std/src/StdChains.sol",
      "solcConfig": {
        "settings": {
          "optimizer": {
            "enabled": true,
            "runs": 200
          },
          "metadata": {
            "bytecodeHash": "ipfs",
            "appendCBOR": true
          },
          "outputSelection": {
            "*": {
              "": [
                "ast"
              ],
              "*": [
                "abi",
                "evm.bytecode",
                "evm.deployedBytecode",
                "evm.methodIdentifiers",
                "metadata"
              ]
            }
          },
          "evmVersion": "paris",
          "libraries": {}
        }
      },
      "imports": [
        "lib/forge-std/src/Vm.sol"
      ],
      "versionRequirement": ">=0.6.2, <0.9.0",
      "artifacts": {
        "StdChains": {
          "0.8.19+commit.7dd6d404.Linux.gcc": "StdChains.sol/StdChains.json"
        }
      }
    },
    "lib/forge-std/src/StdCheats.sol": {
      "lastModificationDate": 1688573043851,
      "contentHash": "24785368b480beef5cd536afd144d5cb",
      "sourceName": "lib/forge-std/src/StdCheats.sol",
      "solcConfig": {
        "settings": {
          "optimizer": {
            "enabled": true,
            "runs": 200
          },
          "metadata": {
            "bytecodeHash": "ipfs",
            "appendCBOR": true
          },
          "outputSelection": {
            "*": {
              "": [
                "ast"
              ],
              "*": [
                "abi",
                "evm.bytecode",
                "evm.deployedBytecode",
                "evm.methodIdentifiers",
                "metadata"
              ]
            }
          },
          "evmVersion": "paris",
          "libraries": {}
        }
      },
      "imports": [
        "lib/forge-std/src/StdStorage.sol",
        "lib/forge-std/src/Vm.sol",
        "lib/forge-std/src/console2.sol"
      ],
      "versionRequirement": ">=0.6.2, <0.9.0",
      "artifacts": {
        "StdCheats": {
          "0.8.19+commit.7dd6d404.Linux.gcc": "StdCheats.sol/StdCheats.json"
        },
        "StdCheatsSafe": {
          "0.8.19+commit.7dd6d404.Linux.gcc": "StdCheats.sol/StdCheatsSafe.json"
        }
      }
    },
    "lib/forge-std/src/StdError.sol": {
      "lastModificationDate": 1688573037001,
      "contentHash": "64c896e1276a291776e5ea5aecb3870a",
      "sourceName": "lib/forge-std/src/StdError.sol",
      "solcConfig": {
        "settings": {
          "optimizer": {
            "enabled": true,
            "runs": 200
          },
          "metadata": {
            "bytecodeHash": "ipfs",
            "appendCBOR": true
          },
          "outputSelection": {
            "*": {
              "": [
                "ast"
              ],
              "*": [
                "abi",
                "evm.bytecode",
                "evm.deployedBytecode",
                "evm.methodIdentifiers",
                "metadata"
              ]
            }
          },
          "evmVersion": "paris",
          "libraries": {}
        }
      },
      "imports": [],
      "versionRequirement": ">=0.6.2, <0.9.0",
      "artifacts": {
        "stdError": {
          "0.8.19+commit.7dd6d404.Linux.gcc": "StdError.sol/stdError.json"
        }
      }
    },
    "lib/forge-std/src/StdInvariant.sol": {
      "lastModificationDate": 1688573043851,
      "contentHash": "12c06010ec43ce935ed209d5aca30828",
      "sourceName": "lib/forge-std/src/StdInvariant.sol",
      "solcConfig": {
        "settings": {
          "optimizer": {
            "enabled": true,
            "runs": 200
          },
          "metadata": {
            "bytecodeHash": "ipfs",
            "appendCBOR": true
          },
          "outputSelection": {
            "*": {
              "": [
                "ast"
              ],
              "*": [
                "abi",
                "evm.bytecode",
                "evm.deployedBytecode",
                "evm.methodIdentifiers",
                "metadata"
              ]
            }
          },
          "evmVersion": "paris",
          "libraries": {}
        }
      },
      "imports": [],
      "versionRequirement": ">=0.6.2, <0.9.0",
      "artifacts": {
        "StdInvariant": {
          "0.8.19+commit.7dd6d404.Linux.gcc": "StdInvariant.sol/StdInvariant.json"
        }
      }
    },
    "lib/forge-std/src/StdJson.sol": {
      "lastModificationDate": 1688573037001,
      "contentHash": "2e1d13674e152408867795362d833c24",
      "sourceName": "lib/forge-std/src/StdJson.sol",
      "solcConfig": {
        "settings": {
          "optimizer": {
            "enabled": true,
            "runs": 200
          },
          "metadata": {
            "bytecodeHash": "ipfs",
            "appendCBOR": true
          },
          "outputSelection": {
            "*": {
              "": [
                "ast"
              ],
              "*": [
                "abi",
                "evm.bytecode",
                "evm.deployedBytecode",
                "evm.methodIdentifiers",
                "metadata"
              ]
            }
          },
          "evmVersion": "paris",
          "libraries": {}
        }
      },
      "imports": [
        "lib/forge-std/src/Vm.sol"
      ],
      "versionRequirement": ">=0.6.0, <0.9.0",
      "artifacts": {
        "stdJson": {
          "0.8.19+commit.7dd6d404.Linux.gcc": "StdJson.sol/stdJson.json"
        }
      }
    },
    "lib/forge-std/src/StdMath.sol": {
      "lastModificationDate": 1688573037001,
      "contentHash": "9da8f453eba6bb98f3d75bc6822bfb29",
      "sourceName": "lib/forge-std/src/StdMath.sol",
      "solcConfig": {
        "settings": {
          "optimizer": {
            "enabled": true,
            "runs": 200
          },
          "metadata": {
            "bytecodeHash": "ipfs",
            "appendCBOR": true
          },
          "outputSelection": {
            "*": {
              "": [
                "ast"
              ],
              "*": [
                "abi",
                "evm.bytecode",
                "evm.deployedBytecode",
                "evm.methodIdentifiers",
                "metadata"
              ]
            }
          },
          "evmVersion": "paris",
          "libraries": {}
        }
      },
      "imports": [],
      "versionRequirement": ">=0.6.2, <0.9.0",
      "artifacts": {
        "stdMath": {
          "0.8.19+commit.7dd6d404.Linux.gcc": "StdMath.sol/stdMath.json"
        }
      }
    },
    "lib/forge-std/src/StdStorage.sol": {
      "lastModificationDate": 1688573037001,
      "contentHash": "3cb9868082df39a53927db09dbc21f23",
      "sourceName": "lib/forge-std/src/StdStorage.sol",
      "solcConfig": {
        "settings": {
          "optimizer": {
            "enabled": true,
            "runs": 200
          },
          "metadata": {
            "bytecodeHash": "ipfs",
            "appendCBOR": true
          },
          "outputSelection": {
            "*": {
              "": [
                "ast"
              ],
              "*": [
                "abi",
                "evm.bytecode",
                "evm.deployedBytecode",
                "evm.methodIdentifiers",
                "metadata"
              ]
            }
          },
          "evmVersion": "paris",
          "libraries": {}
        }
      },
      "imports": [
        "lib/forge-std/src/Vm.sol"
      ],
      "versionRequirement": ">=0.6.2, <0.9.0",
      "artifacts": {
        "stdStorage": {
          "0.8.19+commit.7dd6d404.Linux.gcc": "StdStorage.sol/stdStorage.json"
        },
        "stdStorageSafe": {
          "0.8.19+commit.7dd6d404.Linux.gcc": "StdStorage.sol/stdStorageSafe.json"
        }
      }
    },
    "lib/forge-std/src/StdStyle.sol": {
      "lastModificationDate": 1688573043851,
      "contentHash": "820e6f6b7704f0c980fae604b1e34b18",
      "sourceName": "lib/forge-std/src/StdStyle.sol",
      "solcConfig": {
        "settings": {
          "optimizer": {
            "enabled": true,
            "runs": 200
          },
          "metadata": {
            "bytecodeHash": "ipfs",
            "appendCBOR": true
          },
          "outputSelection": {
            "*": {
              "": [
                "ast"
              ],
              "*": [
                "abi",
                "evm.bytecode",
                "evm.deployedBytecode",
                "evm.methodIdentifiers",
                "metadata"
              ]
            }
          },
          "evmVersion": "paris",
          "libraries": {}
        }
      },
      "imports": [
        "lib/forge-std/src/Vm.sol"
      ],
      "versionRequirement": ">=0.4.22, <0.9.0",
      "artifacts": {
        "StdStyle": {
          "0.8.19+commit.7dd6d404.Linux.gcc": "StdStyle.sol/StdStyle.json"
        }
      }
    },
    "lib/forge-std/src/StdUtils.sol": {
      "lastModificationDate": 1688573043851,
      "contentHash": "dd923493ddd9f98777687205cfe9d646",
      "sourceName": "lib/forge-std/src/StdUtils.sol",
      "solcConfig": {
        "settings": {
          "optimizer": {
            "enabled": true,
            "runs": 200
          },
          "metadata": {
            "bytecodeHash": "ipfs",
            "appendCBOR": true
          },
          "outputSelection": {
            "*": {
              "": [
                "ast"
              ],
              "*": [
                "abi",
                "evm.bytecode",
                "evm.deployedBytecode",
                "evm.methodIdentifiers",
                "metadata"
              ]
            }
          },
          "evmVersion": "paris",
          "libraries": {}
        }
      },
      "imports": [
        "lib/forge-std/src/Vm.sol",
        "lib/forge-std/src/interfaces/IMulticall3.sol"
      ],
      "versionRequirement": ">=0.6.2, <0.9.0",
      "artifacts": {
        "StdUtils": {
          "0.8.19+commit.7dd6d404.Linux.gcc": "StdUtils.sol/StdUtils.json"
        }
      }
    },
    "lib/forge-std/src/Test.sol": {
      "lastModificationDate": 1688573043861,
      "contentHash": "bc9d74a0c612e1c2b66cca2973bcc803",
      "sourceName": "lib/forge-std/src/Test.sol",
      "solcConfig": {
        "settings": {
          "optimizer": {
            "enabled": true,
            "runs": 200
          },
          "metadata": {
            "bytecodeHash": "ipfs",
            "appendCBOR": true
          },
          "outputSelection": {
            "*": {
              "": [
                "ast"
              ],
              "*": [
                "abi",
                "evm.bytecode",
                "evm.deployedBytecode",
                "evm.methodIdentifiers",
                "metadata"
              ]
            }
          },
          "evmVersion": "paris",
          "libraries": {}
        }
      },
      "imports": [
        "lib/forge-std/src/Base.sol",
        "lib/forge-std/src/StdAssertions.sol",
        "lib/forge-std/src/StdChains.sol",
        "lib/forge-std/src/StdCheats.sol",
        "lib/forge-std/src/StdError.sol",
        "lib/forge-std/src/StdInvariant.sol",
        "lib/forge-std/src/StdJson.sol",
        "lib/forge-std/src/StdMath.sol",
        "lib/forge-std/src/StdStorage.sol",
        "lib/forge-std/src/StdStyle.sol",
        "lib/forge-std/src/StdUtils.sol",
        "lib/forge-std/src/Vm.sol",
        "lib/forge-std/src/console.sol",
        "lib/forge-std/src/console2.sol",
        "lib/forge-std/src/interfaces/IMulticall3.sol",
        "lib/solmate/lib/ds-test/src/test.sol"
      ],
      "versionRequirement": ">=0.6.2, <0.9.0",
      "artifacts": {
        "Test": {
          "0.8.19+commit.7dd6d404.Linux.gcc": "Test.sol/Test.json"
        }
      }
    },
    "lib/forge-std/src/Vm.sol": {
      "lastModificationDate": 1688573043861,
      "contentHash": "93cbedbadc52c20145ebbfa27ce148c4",
      "sourceName": "lib/forge-std/src/Vm.sol",
      "solcConfig": {
        "settings": {
          "optimizer": {
            "enabled": true,
            "runs": 200
          },
          "metadata": {
            "bytecodeHash": "ipfs",
            "appendCBOR": true
          },
          "outputSelection": {
            "*": {
              "": [
                "ast"
              ],
              "*": [
                "abi",
                "evm.bytecode",
                "evm.deployedBytecode",
                "evm.methodIdentifiers",
                "metadata"
              ]
            }
          },
          "evmVersion": "paris",
          "libraries": {}
        }
      },
      "imports": [],
      "versionRequirement": ">=0.6.2, <0.9.0",
      "artifacts": {
        "Vm": {
          "0.8.19+commit.7dd6d404.Linux.gcc": "Vm.sol/Vm.json"
        },
        "VmSafe": {
          "0.8.19+commit.7dd6d404.Linux.gcc": "Vm.sol/VmSafe.json"
        }
      }
    },
    "lib/forge-std/src/console.sol": {
      "lastModificationDate": 1688573037001,
      "contentHash": "100b8a33b917da1147740d7ab8b0ded3",
      "sourceName": "lib/forge-std/src/console.sol",
      "solcConfig": {
        "settings": {
          "optimizer": {
            "enabled": true,
            "runs": 200
          },
          "metadata": {
            "bytecodeHash": "ipfs",
            "appendCBOR": true
          },
          "outputSelection": {
            "*": {
              "": [
                "ast"
              ],
              "*": [
                "abi",
                "evm.bytecode",
                "evm.deployedBytecode",
                "evm.methodIdentifiers",
                "metadata"
              ]
            }
          },
          "evmVersion": "paris",
          "libraries": {}
        }
      },
      "imports": [],
      "versionRequirement": ">=0.4.22, <0.9.0",
      "artifacts": {
        "console": {
          "0.8.19+commit.7dd6d404.Linux.gcc": "console.sol/console.json"
        }
      }
    },
    "lib/forge-std/src/console2.sol": {
      "lastModificationDate": 1688573037001,
      "contentHash": "491ca717c1915995e78cc361485a3067",
      "sourceName": "lib/forge-std/src/console2.sol",
      "solcConfig": {
        "settings": {
          "optimizer": {
            "enabled": true,
            "runs": 200
          },
          "metadata": {
            "bytecodeHash": "ipfs",
            "appendCBOR": true
          },
          "outputSelection": {
            "*": {
              "": [
                "ast"
              ],
              "*": [
                "abi",
                "evm.bytecode",
                "evm.deployedBytecode",
                "evm.methodIdentifiers",
                "metadata"
              ]
            }
          },
          "evmVersion": "paris",
          "libraries": {}
        }
      },
      "imports": [],
      "versionRequirement": ">=0.4.22, <0.9.0",
      "artifacts": {
        "console2": {
          "0.8.19+commit.7dd6d404.Linux.gcc": "console2.sol/console2.json"
        }
      }
    },
    "lib/forge-std/src/interfaces/IMulticall3.sol": {
      "lastModificationDate": 1688573037001,
      "contentHash": "7b131ca1ca32ef6378b7b9ad5488b901",
      "sourceName": "lib/forge-std/src/interfaces/IMulticall3.sol",
      "solcConfig": {
        "settings": {
          "optimizer": {
            "enabled": true,
            "runs": 200
          },
          "metadata": {
            "bytecodeHash": "ipfs",
            "appendCBOR": true
          },
          "outputSelection": {
            "*": {
              "": [
                "ast"
              ],
              "*": [
                "abi",
                "evm.bytecode",
                "evm.deployedBytecode",
                "evm.methodIdentifiers",
                "metadata"
              ]
            }
          },
          "evmVersion": "paris",
          "libraries": {}
        }
      },
      "imports": [],
      "versionRequirement": ">=0.6.2, <0.9.0",
      "artifacts": {
        "IMulticall3": {
          "0.8.19+commit.7dd6d404.Linux.gcc": "IMulticall3.sol/IMulticall3.json"
        }
      }
    },
    "lib/foundry-devops/src/DevOpsTools.sol": {
      "lastModificationDate": 1688654776141,
      "contentHash": "61eb7b71f43e938f5da98a2b1212382c",
      "sourceName": "lib/foundry-devops/src/DevOpsTools.sol",
      "solcConfig": {
        "settings": {
          "optimizer": {
            "enabled": true,
            "runs": 200
          },
          "metadata": {
            "bytecodeHash": "ipfs",
            "appendCBOR": true
          },
          "outputSelection": {
            "*": {
              "": [
                "ast"
              ],
              "*": [
                "abi",
                "evm.bytecode",
                "evm.deployedBytecode",
                "evm.methodIdentifiers",
                "metadata"
              ]
            }
          },
          "evmVersion": "paris",
          "libraries": {}
        }
      },
      "imports": [
        "lib/forge-std/src/Vm.sol",
        "lib/forge-std/src/console.sol"
      ],
      "versionRequirement": ">=0.8.13, <0.9.0",
      "artifacts": {
        "DevOpsTools": {
          "0.8.19+commit.7dd6d404.Linux.gcc": "DevOpsTools.sol/DevOpsTools.json"
        }
      }
    },
    "lib/solmate/lib/ds-test/src/test.sol": {
      "lastModificationDate": 1688653703961,
      "contentHash": "962996f0e05d5218857a538a62d7c47e",
      "sourceName": "lib/solmate/lib/ds-test/src/test.sol",
      "solcConfig": {
        "settings": {
          "optimizer": {
            "enabled": true,
            "runs": 200
          },
          "metadata": {
            "bytecodeHash": "ipfs",
            "appendCBOR": true
          },
          "outputSelection": {
            "*": {
              "": [
                "ast"
              ],
              "*": [
                "abi",
                "evm.bytecode",
                "evm.deployedBytecode",
                "evm.methodIdentifiers",
                "metadata"
              ]
            }
          },
          "evmVersion": "paris",
          "libraries": {}
        }
      },
      "imports": [],
      "versionRequirement": ">=0.5.0",
      "artifacts": {
        "DSTest": {
          "0.8.19+commit.7dd6d404.Linux.gcc": "test.sol/DSTest.json"
        }
      }
    },
    "lib/solmate/src/tokens/ERC20.sol": {
      "lastModificationDate": 1688653702971,
      "contentHash": "0c7c7ada139062536af09d69d96d395c",
      "sourceName": "lib/solmate/src/tokens/ERC20.sol",
      "solcConfig": {
        "settings": {
          "optimizer": {
            "enabled": true,
            "runs": 200
          },
          "metadata": {
            "bytecodeHash": "ipfs",
            "appendCBOR": true
          },
          "outputSelection": {
            "*": {
              "": [
                "ast"
              ],
              "*": [
                "abi",
                "evm.bytecode",
                "evm.deployedBytecode",
                "evm.methodIdentifiers",
                "metadata"
              ]
            }
          },
          "evmVersion": "paris",
          "libraries": {}
        }
      },
      "imports": [],
      "versionRequirement": ">=0.8.0",
      "artifacts": {
        "ERC20": {
          "0.8.19+commit.7dd6d404.Linux.gcc": "ERC20.sol/ERC20.json"
        }
      }
    },
    "script/DeployRaffle.s.sol": {
      "lastModificationDate": 1688661168310,
      "contentHash": "2e033716905dbf785223e71057e6d91b",
      "sourceName": "script/DeployRaffle.s.sol",
      "solcConfig": {
        "settings": {
          "optimizer": {
            "enabled": true,
            "runs": 200
          },
          "metadata": {
            "bytecodeHash": "ipfs",
            "appendCBOR": true
          },
          "outputSelection": {
            "*": {
              "": [
                "ast"
              ],
              "*": [
                "abi",
                "evm.bytecode",
                "evm.deployedBytecode",
                "evm.methodIdentifiers",
                "metadata"
              ]
            }
          },
          "evmVersion": "paris",
          "libraries": {}
        }
      },
      "imports": [
        "lib/chainlink-brownie-contracts/contracts/src/v0.8/VRFConsumerBaseV2.sol",
        "lib/chainlink-brownie-contracts/contracts/src/v0.8/interfaces/LinkTokenInterface.sol",
        "lib/chainlink-brownie-contracts/contracts/src/v0.8/interfaces/VRFCoordinatorV2Interface.sol",
        "lib/chainlink-brownie-contracts/contracts/src/v0.8/mocks/VRFCoordinatorV2Mock.sol",
        "lib/forge-std/src/Base.sol",
        "lib/forge-std/src/Script.sol",
        "lib/forge-std/src/StdChains.sol",
        "lib/forge-std/src/StdCheats.sol",
        "lib/forge-std/src/StdJson.sol",
        "lib/forge-std/src/StdMath.sol",
        "lib/forge-std/src/StdStorage.sol",
        "lib/forge-std/src/StdUtils.sol",
        "lib/forge-std/src/Vm.sol",
        "lib/forge-std/src/console.sol",
        "lib/forge-std/src/console2.sol",
        "lib/forge-std/src/interfaces/IMulticall3.sol",
        "lib/foundry-devops/src/DevOpsTools.sol",
        "lib/solmate/src/tokens/ERC20.sol",
        "script/HelperConfig.s.sol",
        "script/Interactions.s.sol",
        "src/Raffle.sol",
        "test/mocks/LinkToken.sol"
      ],
      "versionRequirement": "^0.8.18",
      "artifacts": {
        "DeployRaffle": {
          "0.8.19+commit.7dd6d404.Linux.gcc": "DeployRaffle.s.sol/DeployRaffle.json"
        }
      }
    },
    "script/HelperConfig.s.sol": {
      "lastModificationDate": 1688661226470,
      "contentHash": "37e3a319f6aadce4c0243cc8e05b919a",
      "sourceName": "script/HelperConfig.s.sol",
      "solcConfig": {
        "settings": {
          "optimizer": {
            "enabled": true,
            "runs": 200
          },
          "metadata": {
            "bytecodeHash": "ipfs",
            "appendCBOR": true
          },
          "outputSelection": {
            "*": {
              "": [
                "ast"
              ],
              "*": [
                "abi",
                "evm.bytecode",
                "evm.deployedBytecode",
                "evm.methodIdentifiers",
                "metadata"
              ]
            }
          },
          "evmVersion": "paris",
          "libraries": {}
        }
      },
      "imports": [
        "lib/chainlink-brownie-contracts/contracts/src/v0.8/VRFConsumerBaseV2.sol",
        "lib/chainlink-brownie-contracts/contracts/src/v0.8/interfaces/LinkTokenInterface.sol",
        "lib/chainlink-brownie-contracts/contracts/src/v0.8/interfaces/VRFCoordinatorV2Interface.sol",
        "lib/chainlink-brownie-contracts/contracts/src/v0.8/mocks/VRFCoordinatorV2Mock.sol",
        "lib/forge-std/src/Base.sol",
        "lib/forge-std/src/Script.sol",
        "lib/forge-std/src/StdChains.sol",
        "lib/forge-std/src/StdCheats.sol",
        "lib/forge-std/src/StdJson.sol",
        "lib/forge-std/src/StdMath.sol",
        "lib/forge-std/src/StdStorage.sol",
        "lib/forge-std/src/StdUtils.sol",
        "lib/forge-std/src/Vm.sol",
        "lib/forge-std/src/console.sol",
        "lib/forge-std/src/console2.sol",
        "lib/forge-std/src/interfaces/IMulticall3.sol",
        "lib/solmate/src/tokens/ERC20.sol",
        "src/Raffle.sol",
        "test/mocks/LinkToken.sol"
      ],
      "versionRequirement": "^0.8.18",
      "artifacts": {
        "HelperConfig": {
          "0.8.19+commit.7dd6d404.Linux.gcc": "HelperConfig.s.sol/HelperConfig.json"
        }
      }
    },
    "script/Interactions.s.sol": {
      "lastModificationDate": 1688661102681,
      "contentHash": "8256c766377a6355474533a3796baaa8",
      "sourceName": "script/Interactions.s.sol",
      "solcConfig": {
        "settings": {
          "optimizer": {
            "enabled": true,
            "runs": 200
          },
          "metadata": {
            "bytecodeHash": "ipfs",
            "appendCBOR": true
          },
          "outputSelection": {
            "*": {
              "": [
                "ast"
              ],
              "*": [
                "abi",
                "evm.bytecode",
                "evm.deployedBytecode",
                "evm.methodIdentifiers",
                "metadata"
              ]
            }
          },
          "evmVersion": "paris",
          "libraries": {}
        }
      },
      "imports": [
        "lib/chainlink-brownie-contracts/contracts/src/v0.8/VRFConsumerBaseV2.sol",
        "lib/chainlink-brownie-contracts/contracts/src/v0.8/interfaces/LinkTokenInterface.sol",
        "lib/chainlink-brownie-contracts/contracts/src/v0.8/interfaces/VRFCoordinatorV2Interface.sol",
        "lib/chainlink-brownie-contracts/contracts/src/v0.8/mocks/VRFCoordinatorV2Mock.sol",
        "lib/forge-std/src/Base.sol",
        "lib/forge-std/src/Script.sol",
        "lib/forge-std/src/StdChains.sol",
        "lib/forge-std/src/StdCheats.sol",
        "lib/forge-std/src/StdJson.sol",
        "lib/forge-std/src/StdMath.sol",
        "lib/forge-std/src/StdStorage.sol",
        "lib/forge-std/src/StdUtils.sol",
        "lib/forge-std/src/Vm.sol",
        "lib/forge-std/src/console.sol",
        "lib/forge-std/src/console2.sol",
        "lib/forge-std/src/interfaces/IMulticall3.sol",
        "lib/foundry-devops/src/DevOpsTools.sol",
        "lib/solmate/src/tokens/ERC20.sol",
        "script/HelperConfig.s.sol",
        "src/Raffle.sol",
        "test/mocks/LinkToken.sol"
      ],
      "versionRequirement": "^0.8.18",
      "artifacts": {
        "AddConsumer": {
          "0.8.19+commit.7dd6d404.Linux.gcc": "Interactions.s.sol/AddConsumer.json"
        },
        "CreateSubscription": {
          "0.8.19+commit.7dd6d404.Linux.gcc": "Interactions.s.sol/CreateSubscription.json"
        },
        "FundSubscription": {
          "0.8.19+commit.7dd6d404.Linux.gcc": "Interactions.s.sol/FundSubscription.json"
        }
      }
    },
    "src/Raffle.sol": {
      "lastModificationDate": 1688659585331,
      "contentHash": "caa99db6f0bb51711295606a6679b529",
      "sourceName": "src/Raffle.sol",
      "solcConfig": {
        "settings": {
          "optimizer": {
            "enabled": true,
            "runs": 200
          },
          "metadata": {
            "bytecodeHash": "ipfs",
            "appendCBOR": true
          },
          "outputSelection": {
            "*": {
              "": [
                "ast"
              ],
              "*": [
                "abi",
                "evm.bytecode",
                "evm.deployedBytecode",
                "evm.methodIdentifiers",
                "metadata"
              ]
            }
          },
          "evmVersion": "paris",
          "libraries": {}
        }
      },
      "imports": [
        "lib/chainlink-brownie-contracts/contracts/src/v0.8/VRFConsumerBaseV2.sol",
        "lib/chainlink-brownie-contracts/contracts/src/v0.8/interfaces/VRFCoordinatorV2Interface.sol"
      ],
      "versionRequirement": "^0.8.18",
      "artifacts": {
        "Raffle": {
          "0.8.19+commit.7dd6d404.Linux.gcc": "Raffle.sol/Raffle.json"
        }
      }
    },
    "test/mocks/LinkToken.sol": {
      "lastModificationDate": 1688653734331,
      "contentHash": "e61feab8bb36626081f8ce3e7a1a25f3",
      "sourceName": "test/mocks/LinkToken.sol",
      "solcConfig": {
        "settings": {
          "optimizer": {
            "enabled": true,
            "runs": 200
          },
          "metadata": {
            "bytecodeHash": "ipfs",
            "appendCBOR": true
          },
          "outputSelection": {
            "*": {
              "": [
                "ast"
              ],
              "*": [
                "abi",
                "evm.bytecode",
                "evm.deployedBytecode",
                "evm.methodIdentifiers",
                "metadata"
              ]
            }
          },
          "evmVersion": "paris",
          "libraries": {}
        }
      },
      "imports": [
        "lib/solmate/src/tokens/ERC20.sol"
      ],
      "versionRequirement": "^0.8.0",
      "artifacts": {
        "ERC677Receiver": {
          "0.8.19+commit.7dd6d404.Linux.gcc": "LinkToken.sol/ERC677Receiver.json"
        },
        "LinkToken": {
          "0.8.19+commit.7dd6d404.Linux.gcc": "LinkToken.sol/LinkToken.json"
        }
      }
    },
    "test/unit/RaffleTest.t.sol": {
      "lastModificationDate": 1688661192760,
      "contentHash": "f402721ea18c306bac8c92d338a4ce64",
      "sourceName": "test/unit/RaffleTest.t.sol",
      "solcConfig": {
        "settings": {
          "optimizer": {
            "enabled": true,
            "runs": 200
          },
          "metadata": {
            "bytecodeHash": "ipfs",
            "appendCBOR": true
          },
          "outputSelection": {
            "*": {
              "": [
                "ast"
              ],
              "*": [
                "abi",
                "evm.bytecode",
                "evm.deployedBytecode",
                "evm.methodIdentifiers",
                "metadata"
              ]
            }
          },
          "evmVersion": "paris",
          "libraries": {}
        }
      },
      "imports": [
        "lib/chainlink-brownie-contracts/contracts/src/v0.8/VRFConsumerBaseV2.sol",
        "lib/chainlink-brownie-contracts/contracts/src/v0.8/interfaces/LinkTokenInterface.sol",
        "lib/chainlink-brownie-contracts/contracts/src/v0.8/interfaces/VRFCoordinatorV2Interface.sol",
        "lib/chainlink-brownie-contracts/contracts/src/v0.8/mocks/VRFCoordinatorV2Mock.sol",
        "lib/forge-std/src/Base.sol",
        "lib/forge-std/src/Script.sol",
        "lib/forge-std/src/StdAssertions.sol",
        "lib/forge-std/src/StdChains.sol",
        "lib/forge-std/src/StdCheats.sol",
        "lib/forge-std/src/StdError.sol",
        "lib/forge-std/src/StdInvariant.sol",
        "lib/forge-std/src/StdJson.sol",
        "lib/forge-std/src/StdMath.sol",
        "lib/forge-std/src/StdStorage.sol",
        "lib/forge-std/src/StdStyle.sol",
        "lib/forge-std/src/StdUtils.sol",
        "lib/forge-std/src/Test.sol",
        "lib/forge-std/src/Vm.sol",
        "lib/forge-std/src/console.sol",
        "lib/forge-std/src/console2.sol",
        "lib/forge-std/src/interfaces/IMulticall3.sol",
        "lib/foundry-devops/src/DevOpsTools.sol",
        "lib/solmate/lib/ds-test/src/test.sol",
        "lib/solmate/src/tokens/ERC20.sol",
        "script/DeployRaffle.s.sol",
        "script/HelperConfig.s.sol",
        "script/Interactions.s.sol",
        "src/Raffle.sol",
        "test/mocks/LinkToken.sol"
      ],
      "versionRequirement": "^0.8.18",
      "artifacts": {
        "RaffleTest": {
          "0.8.19+commit.7dd6d404.Linux.gcc": "RaffleTest.t.sol/RaffleTest.json"
        }
      }
    }
  }
}